odoo9_addon_account_invoice_fiscal_position_update-9.0.1.0.0-py2.7-nspkg.pth
odoo_addons/account_invoice_fiscal_position_update/__openerp__.py
odoo_addons/account_invoice_fiscal_position_update/__init__.py
odoo_addons/account_invoice_fiscal_position_update/README.rst
odoo_addons/account_invoice_fiscal_position_update/models/account_invoice.py
odoo_addons/account_invoice_fiscal_position_update/models/__init__.py
odoo_addons/account_invoice_fiscal_position_update/i18n/zh_CN.po
odoo_addons/account_invoice_fiscal_position_update/i18n/it.po
odoo_addons/account_invoice_fiscal_position_update/i18n/es.po
odoo_addons/account_invoice_fiscal_position_update/i18n/sl.po
odoo_addons/account_invoice_fiscal_position_update/i18n/nl.po
odoo_addons/account_invoice_fiscal_position_update/i18n/fr.po
odoo_addons/account_invoice_fiscal_position_update/i18n/pt_BR.po
odoo_addons/account_invoice_fiscal_position_update/tests/test_account_invoice.py
odoo_addons/account_invoice_fiscal_position_update/tests/__init__.py
odoo_addons/account_invoice_fiscal_position_update/static/description/icon.png
odoo9_addon_account_invoice_fiscal_position_update-9.0.1.0.0.dist-info/top_level.txt
odoo9_addon_account_invoice_fiscal_position_update-9.0.1.0.0.dist-info/WHEEL
odoo9_addon_account_invoice_fiscal_position_update-9.0.1.0.0.dist-info/RECORD
odoo9_addon_account_invoice_fiscal_position_update-9.0.1.0.0.dist-info/metadata.json
odoo9_addon_account_invoice_fiscal_position_update-9.0.1.0.0.dist-info/DESCRIPTION.rst
odoo9_addon_account_invoice_fiscal_position_update-9.0.1.0.0.dist-info/METADATA
odoo9_addon_account_invoice_fiscal_position_update-9.0.1.0.0.dist-info/namespace_packages.txt
